hftu/__init__.py
hftu/folding.py
hftu/hftu.py
hftu/init.py
hftu/optimization.py
hftu/plot.py
hftu/test_hftu.py
hftu/test_perf.py
hftu/types.py
hftu-1.0.3.dist-info/LICENSE
hftu-1.0.3.dist-info/METADATA
hftu-1.0.3.dist-info/WHEEL
hftu-1.0.3.dist-info/top_level.txt
hftu-1.0.3.dist-info/RECORD
