Metadata-Version: 2.1
Name: hftu
Version: 1.0.3
Summary: A package to compute the hyperplane folding test of unimodality
Home-page: UNKNOWN
Author: asr
Author-email: UNKNOWN
License: UNKNOWN
Platform: UNKNOWN
